dota2gsipy/__init__.py
dota2gsipy/gamestate.py
dota2gsipy/map.py
dota2gsipy/player.py
dota2gsipy/provider.py
dota2gsipy/server.py
dota2gsipy/hero/__init__.py
dota2gsipy/hero/ability.py
dota2gsipy/hero/hero.py
dota2gsipy/hero/item.py
dota2gsipy-0.1.0.dist-info/METADATA
dota2gsipy-0.1.0.dist-info/WHEEL
dota2gsipy-0.1.0.dist-info/top_level.txt
dota2gsipy-0.1.0.dist-info/RECORD
